{
  "updatedAt": "2026-07-17T06:59:23.972733+09:00",
  "count": 9,
  "items": [
    {
      "title": "「第13回厚生科学審議会食品衛生監視部会」の開催について",
      "pubDate": "2026-07-15T14:00:00+09:00",
      "link": "https://www.mhlw.go.jp/stf/newpage_74568.html",
      "source": "mhlw"
    },
    {
      "title": "第１回 令和８年度医師の働き方改革の推進等に関する検討会：資料",
      "pubDate": "2026-07-13T10:00:00+09:00",
      "link": "https://www.mhlw.go.jp/stf/newpage_74139.html",
      "source": "mhlw"
    },
    {
      "title": "中央最低賃金審議会 (目安に関する小委員会)",
      "pubDate": "2026-07-10T18:00:00+09:00",
      "link": "https://www.mhlw.go.jp/stf/shingi/shingi-tingin_127941.html",
      "source": "mhlw"
    },
    {
      "title": "令和８年度中央最低賃金審議会目安に関する小委員会（第２回）資料",
      "pubDate": "2026-07-10T13:00:00+09:00",
      "link": "https://www.mhlw.go.jp/stf/newpage_74463.html",
      "source": "mhlw"
    },
    {
      "title": "令和８年度第３回化学物質管理に係る専門家検討会を開催します",
      "pubDate": "2026-07-09T14:00:00+09:00",
      "link": "https://www.mhlw.go.jp/stf/newpage_74297.html",
      "source": "mhlw"
    },
    {
      "title": "第１回 令和８年度医師の働き方改革の推進等に関する検討会：開催案内",
      "pubDate": "2026-07-08T14:00:00+09:00",
      "link": "https://www.mhlw.go.jp/stf/newpage_74111.html",
      "source": "mhlw"
    },
    {
      "title": "令和８年度医師の働き方改革の推進等に関する検討会",
      "pubDate": "2026-07-08T14:00:00+09:00",
      "link": "https://www.mhlw.go.jp/stf/newpage_74108.html",
      "source": "mhlw"
    },
    {
      "title": "令和８年度老人保健健康増進等事業（老人保健事業推進費等補助金）の国庫補助協議（追加公募）について",
      "pubDate": "2026-07-03T15:09:00+09:00",
      "link": "https://www.mhlw.go.jp/stf/newpage_74285.html",
      "source": "mhlw"
    },
    {
      "title": "令和８年度社会福祉施設等施設整備費補助金の内示について（令和８年度当初予算等）",
      "pubDate": "2026-07-02T14:00:00+09:00",
      "link": "https://www.mhlw.go.jp/stf/newpage_74201.html",
      "source": "mhlw"
    }
  ]
}